{
  "band": "mass-malayalam",
  "generated": "2026-06-26T04:24:35+05:30",
  "slots": [
    {
      "youtube": "zI8sWVDlZMI",
      "title": "Simhasanam",
      "start": "2026-06-26T03:00:00+05:30",
      "end": "2026-06-26T05:28:20+05:30",
      "segments": [
        {
          "from": 0,
          "to": 8900
        }
      ]
    },
    {
      "youtube": "AzwfbCCouLE",
      "title": "Onnaman",
      "start": "2026-06-26T05:28:20+05:30",
      "end": "2026-06-26T08:16:21+05:30",
      "segments": [
        {
          "from": 0,
          "to": 10081
        }
      ]
    },
    {
      "youtube": "cxW9_c15JHg",
      "title": "Sathyameva Jayathe",
      "start": "2026-06-26T08:16:21+05:30",
      "end": "2026-06-26T11:05:18+05:30",
      "segments": [
        {
          "from": 0,
          "to": 10137
        }
      ]
    },
    {
      "youtube": "KmRVJ8ZFew0",
      "title": "Vazhunnor",
      "start": "2026-06-26T11:05:18+05:30",
      "end": "2026-06-26T13:40:27+05:30",
      "segments": [
        {
          "from": 0,
          "to": 9309
        }
      ]
    },
    {
      "youtube": "I5eQkEBVoYo",
      "title": "Praja",
      "start": "2026-06-26T13:40:27+05:30",
      "end": "2026-06-26T16:37:31+05:30",
      "segments": [
        {
          "from": 0,
          "to": 10624
        }
      ]
    },
    {
      "youtube": "H88LQE0vJRw",
      "title": "Harikrishnans",
      "start": "2026-06-26T16:37:31+05:30",
      "end": "2026-06-26T19:11:51+05:30",
      "segments": [
        {
          "from": 0,
          "to": 9260
        }
      ]
    },
    {
      "youtube": "1sEWgYDJjPw",
      "title": "Olympian Anthony Adam",
      "start": "2026-06-26T19:11:51+05:30",
      "end": "2026-06-26T21:44:53+05:30",
      "segments": [
        {
          "from": 0,
          "to": 9182
        }
      ]
    },
    {
      "youtube": "sX-mOuh6FY0",
      "title": "Pingami",
      "start": "2026-06-26T21:44:53+05:30",
      "end": "2026-06-27T24:03:38+05:30",
      "segments": [
        {
          "from": 0,
          "to": 8325
        }
      ]
    },
    {
      "youtube": "E45xT6pWM2M",
      "title": "Adhwaytham",
      "start": "2026-06-27T24:03:38+05:30",
      "end": "2026-06-27T02:56:32+05:30",
      "segments": [
        {
          "from": 0,
          "to": 10374
        }
      ]
    },
    {
      "youtube": "nUQre7zjGKE",
      "title": "Ekalavyan",
      "start": "2026-06-27T02:56:32+05:30",
      "end": "2026-06-27T05:35:03+05:30",
      "segments": [
        {
          "from": 0,
          "to": 9511
        }
      ]
    }
  ]
}